Metadata-Version: 1.1
Name: morsify
Version: 0.1
Summary: Convert alphanumeric text to morse
Home-page: http://www.github.com/shashank9830
Author: Shashank Singh
Author-email: shashank9830@gmail.com
License: UNKNOWN
Download-URL: http://www.github.com/shashank9830
Platform: UNKNOWN
